{
  "standings": {
    "brazil_serie_a": [
      {
        "rank": 1,
        "team": {
          "id": 619,
          "name": "SE Palmeiras",
          "logo": "https://cdn.footystats.org/img/teams/brazil-se-palmeiras.png"
        },
        "points": 19,
        "goalsDiff": 9,
        "group": "Brazil Serie A 2026",
        "status": "same",
        "description": "Copa Libertadores",
        "all": {
          "played": 8,
          "win": 6,
          "draw": 1,
          "lose": 1,
          "goals": {
            "for": 17,
            "against": 8
          },
          "form": "WLWWW",
          "btts_matches": 6,
          "avg_corners_per_game": 4.5,
          "aproveitamento": 79.2,
          "over_2_5_goals": 6,
          "over_0_5_ht": 8,
          "over_0_5_ft": 4,
          "clean_sheets": 2
        },
        "home": {
          "played": 4,
          "win": 4,
          "draw": 0,
          "lose": 0,
          "goals": {
            "for": 10,
            "against": 3
          },
          "form_home": "WWWW",
          "avg_corners_home_per_game": 4.75,
          "aproveitamento_home": 100.0,
          "btts_home_matches": 3,
          "over_2_5_goals_home": 3,
          "over_0_5_ht_home": 4,
          "over_0_5_ft_home": 2,
          "clean_sheets_home": 1
        },
        "away": {
          "played": 4,
          "win": 2,
          "draw": 1,
          "lose": 1,
          "goals": {
            "for": 7,
            "against": 5
          },
          "form_visitor": "DWLW",
          "btts_away_matches": 3,
          "avg_corners_away_per_game": 4.25,
          "aproveitamento_away": 58.3,
          "over_2_5_goals_away": 3,
          "over_0_5_ht_away": 4,
          "over_0_5_ft_away": 2,
          "clean_sheets_away": 1
        },
        "update": "2025-09-23T00:00:00+00:00"
      },
      {
        "rank": 2,
        "team": {
          "id": 618,
          "name": "São Paulo FC",
          "logo": "https://cdn.footystats.org/img/teams/brazil-sao-paulo-fc.png"
        },
        "points": 16,
        "goalsDiff": 5,
        "group": "Brazil Serie A 2026",
        "status": "same",
        "description": "Copa Libertadores",
        "all": {
          "played": 8,
          "win": 5,
          "draw": 1,
          "lose": 2,
          "goals": {
            "for": 10,
            "against": 5
          },
          "form": "WWWLL",
          "btts_matches": 3,
          "avg_corners_per_game": 5.25,
          "aproveitamento": 66.7,
          "over_2_5_goals": 2,
          "over_0_5_ht": 1,
          "over_0_5_ft": 6,
          "clean_sheets": 3
        },
        "home": {
          "played": 4,
          "win": 3,
          "draw": 0,
          "lose": 1,
          "goals": {
            "for": 6,
            "against": 2
          },
          "form_home": "WWWL",
          "avg_corners_home_per_game": 6.5,
          "aproveitamento_home": 75.0,
          "btts_home_matches": 1,
          "over_2_5_goals_home": 1,
          "over_0_5_ht_home": 1,
          "over_0_5_ft_home": 3,
          "clean_sheets_home": 2
        },
        "away": {
          "played": 4,
          "win": 2,
          "draw": 1,
          "lose": 1,
          "goals": {
            "for": 4,
            "against": 3
          },
          "form_visitor": "DWWL",
          "btts_away_matches": 2,
          "avg_corners_away_per_game": 4.0,
          "aproveitamento_away": 58.3,
          "over_2_5_goals_away": 1,
          "over_0_5_ht_away": 0,
          "over_0_5_ft_away": 3,
          "clean_sheets_away": 1
        },
        "update": "2025-09-23T00:00:00+00:00"
      },
      {
        "rank": 3,
        "team": {
          "id": 617,
          "name": "Fluminense FC",
          "logo": "https://cdn.footystats.org/img/teams/brazil-fluminense-fc.png"
        },
        "points": 16,
        "goalsDiff": 4,
        "group": "Brazil Serie A 2026",
        "status": "same",
        "description": "Copa Libertadores",
        "all": {
          "played": 8,
          "win": 5,
          "draw": 1,
          "lose": 2,
          "goals": {
            "for": 13,
            "against": 9
          },
          "form": "LWWLW",
          "btts_matches": 5,
          "avg_corners_per_game": 5.12,
          "aproveitamento": 66.7,
          "over_2_5_goals": 4,
          "over_0_5_ht": 6,
          "over_0_5_ft": 5,
          "clean_sheets": 3
        },
        "home": {
          "played": 4,
          "win": 4,
          "draw": 0,
          "lose": 0,
          "goals": {
            "for": 7,
            "against": 3
          },
          "form_home": "WWWW",
          "avg_corners_home_per_game": 4.25,
          "aproveitamento_home": 100.0,
          "btts_home_matches": 2,
          "over_2_5_goals_home": 2,
          "over_0_5_ht_home": 2,
          "over_0_5_ft_home": 3,
          "clean_sheets_home": 2
        },
        "away": {
          "played": 4,
          "win": 1,
          "draw": 1,
          "lose": 2,
          "goals": {
            "for": 6,
            "against": 6
          },
          "form_visitor": "DLWL",
          "btts_away_matches": 3,
          "avg_corners_away_per_game": 6.0,
          "aproveitamento_away": 33.3,
          "over_2_5_goals_away": 2,
          "over_0_5_ht_away": 4,
          "over_0_5_ft_away": 2,
          "clean_sheets_away": 1
        },
        "update": "2025-09-23T00:00:00+00:00"
      },
      {
        "rank": 4,
        "team": {
          "id": 612,
          "name": "CR Flamengo",
          "logo": "https://cdn.footystats.org/img/teams/brazil-cr-flamengo.png"
        },
        "points": 14,
        "goalsDiff": 8,
        "group": "Brazil Serie A 2026",
        "status": "same",
        "description": "Copa Libertadores",
        "all": {
          "played": 7,
          "win": 4,
          "draw": 2,
          "lose": 1,
          "goals": {
            "for": 13,
            "against": 5
          },
          "form": "WWWWD",
          "btts_matches": 4,
          "avg_corners_per_game": 4.14,
          "aproveitamento": 66.7,
          "over_2_5_goals": 4,
          "over_0_5_ht": 5,
          "over_0_5_ft": 5,
          "clean_sheets": 3
        },
        "home": {
          "played": 3,
          "win": 2,
          "draw": 1,
          "lose": 0,
          "goals": {
            "for": 6,
            "against": 1
          },
          "form_home": "DWW",
          "avg_corners_home_per_game": 5.0,
          "aproveitamento_home": 77.8,
          "btts_home_matches": 1,
          "over_2_5_goals_home": 1,
          "over_0_5_ht_home": 2,
          "over_0_5_ft_home": 3,
          "clean_sheets_home": 2
        },
        "away": {
          "played": 4,
          "win": 2,
          "draw": 1,
          "lose": 1,
          "goals": {
            "for": 7,
            "against": 4
          },
          "form_visitor": "LWWD",
          "btts_away_matches": 3,
          "avg_corners_away_per_game": 3.5,
          "aproveitamento_away": 58.3,
          "over_2_5_goals_away": 3,
          "over_0_5_ht_away": 3,
          "over_0_5_ft_away": 2,
          "clean_sheets_away": 1
        },
        "update": "2025-09-23T00:00:00+00:00"
      },
      {
        "rank": 5,
        "team": {
          "id": 626,
          "name": "EC Bahia",
          "logo": "https://cdn.footystats.org/img/teams/brazil-ec-bahia.png"
        },
        "points": 14,
        "goalsDiff": 2,
        "group": "Brazil Serie A 2026",
        "status": "same",
        "description": "Copa Sul-Americana",
        "all": {
          "played": 7,
          "win": 4,
          "draw": 2,
          "lose": 1,
          "goals": {
            "for": 9,
            "against": 7
          },
          "form": "WDWWL",
          "btts_matches": 4,
          "avg_corners_per_game": 5.71,
          "aproveitamento": 66.7,
          "over_2_5_goals": 2,
          "over_0_5_ht": 6,
          "over_0_5_ft": 1,
          "clean_sheets": 3
        },
        "home": {
          "played": 3,
          "win": 1,
          "draw": 2,
          "lose": 0,
          "goals": {
            "for": 4,
            "against": 2
          },
          "form_home": "DDW",
          "avg_corners_home_per_game": 6.67,
          "aproveitamento_home": 55.6,
          "btts_home_matches": 2,
          "over_2_5_goals_home": 0,
          "over_0_5_ht_home": 2,
          "over_0_5_ft_home": 1,
          "clean_sheets_home": 1
        },
        "away": {
          "played": 4,
          "win": 3,
          "draw": 0,
          "lose": 1,
          "goals": {
            "for": 5,
            "against": 5
          },
          "form_visitor": "WWWL",
          "btts_away_matches": 2,
          "avg_corners_away_per_game": 5.0,
          "aproveitamento_away": 75.0,
          "over_2_5_goals_away": 2,
          "over_0_5_ht_away": 4,
          "over_0_5_ft_away": 0,
          "clean_sheets_away": 2
        },
        "update": "2025-09-23T00:00:00+00:00"
      },
      {
        "rank": 6,
        "team": {
          "id": 622,
          "name": "CA Paranaense",
          "logo": "https://cdn.footystats.org/img/teams/brazil-ca-paranaense.png"
        },
        "points": 13,
        "goalsDiff": 3,
        "group": "Brazil Serie A 2026",
        "status": "same",
        "description": "Copa Sul-Americana",
        "all": {
          "played": 7,
          "win": 4,
          "draw": 1,
          "lose": 2,
          "goals": {
            "for": 10,
            "against": 7
          },
          "form": "LDLWW",
          "btts_matches": 4,
          "avg_corners_per_game": 5.14,
          "aproveitamento": 61.9,
          "over_2_5_goals": 3,
          "over_0_5_ht": 5,
          "over_0_5_ft": 4,
          "clean_sheets": 2
        },
        "home": {
          "played": 4,
          "win": 3,
          "draw": 0,
          "lose": 1,
          "goals": {
            "for": 6,
            "against": 3
          },
          "form_home": "WLWW",
          "avg_corners_home_per_game": 6.75,
          "aproveitamento_home": 75.0,
          "btts_home_matches": 2,
          "over_2_5_goals_home": 2,
          "over_0_5_ht_home": 3,
          "over_0_5_ft_home": 2,
          "clean_sheets_home": 1
        },
        "away": {
          "played": 3,
          "win": 1,
          "draw": 1,
          "lose": 1,
          "goals": {
            "for": 4,
            "against": 4
          },
          "form_visitor": "WDL",
          "btts_away_matches": 2,
          "avg_corners_away_per_game": 3.0,
          "aproveitamento_away": 44.4,
          "over_2_5_goals_away": 1,
          "over_0_5_ht_away": 2,
          "over_0_5_ft_away": 2,
          "clean_sheets_away": 1
        },
        "update": "2025-09-23T00:00:00+00:00"
      },
      {
        "rank": 7,
        "team": {
          "id": 627,
          "name": "Coritiba FBC",
          "logo": "https://cdn.footystats.org/img/teams/brazil-coritiba-fbc.png"
        },
        "points": 13,
        "goalsDiff": 1,
        "group": "Brazil Serie A 2026",
        "status": "same",
        "description": "",
        "all": {
          "played": 8,
          "win": 4,
          "draw": 1,
          "lose": 3,
          "goals": {
            "for": 9,
            "against": 8
          },
          "form": "LWWWL",
          "btts_matches": 2,
          "avg_corners_per_game": 3.38,
          "aproveitamento": 54.2,
          "over_2_5_goals": 2,
          "over_0_5_ht": 4,
          "over_0_5_ft": 4,
          "clean_sheets": 3
        },
        "home": {
          "played": 3,
          "win": 1,
          "draw": 0,
          "lose": 2,
          "goals": {
            "for": 1,
            "against": 2
          },
          "form_home": "LLW",
          "avg_corners_home_per_game": 2.67,
          "aproveitamento_home": 33.3,
          "btts_home_matches": 0,
          "over_2_5_goals_home": 0,
          "over_0_5_ht_home": 1,
          "over_0_5_ft_home": 0,
          "clean_sheets_home": 1
        },
        "away": {
          "played": 5,
          "win": 3,
          "draw": 1,
          "lose": 1,
          "goals": {
            "for": 8,
            "against": 6
          },
          "form_visitor": "WDWWL",
          "btts_away_matches": 2,
          "avg_corners_away_per_game": 3.8,
          "aproveitamento_away": 66.7,
          "over_2_5_goals_away": 2,
          "over_0_5_ht_away": 3,
          "over_0_5_ft_away": 4,
          "clean_sheets_away": 2
        },
        "update": "2025-09-23T00:00:00+00:00"
      },
      {
        "rank": 8,
        "team": {
          "id": 616,
          "name": "Grêmio FB Porto Alegrense",
          "logo": "https://cdn.footystats.org/img/teams/brazil-gremio-fb-porto-alegrense.png"
        },
        "points": 11,
        "goalsDiff": 1,
        "group": "Brazil Serie A 2026",
        "status": "same",
        "description": "",
        "all": {
          "played": 8,
          "win": 3,
          "draw": 2,
          "lose": 3,
          "goals": {
            "for": 13,
            "against": 12
          },
          "form": "WDDWL",
          "btts_matches": 6,
          "avg_corners_per_game": 4.25,
          "aproveitamento": 45.8,
          "over_2_5_goals": 4,
          "over_0_5_ht": 5,
          "over_0_5_ft": 4,
          "clean_sheets": 1
        },
        "home": {
          "played": 4,
          "win": 3,
          "draw": 1,
          "lose": 0,
          "goals": {
            "for": 10,
            "against": 5
          },
          "form_home": "WWDW",
          "avg_corners_home_per_game": 4.5,
          "aproveitamento_home": 83.3,
          "btts_home_matches": 3,
          "over_2_5_goals_home": 2,
          "over_0_5_ht_home": 3,
          "over_0_5_ft_home": 3,
          "clean_sheets_home": 1
        },
        "away": {
          "played": 4,
          "win": 0,
          "draw": 1,
          "lose": 3,
          "goals": {
            "for": 3,
            "against": 7
          },
          "form_visitor": "LLDL",
          "btts_away_matches": 3,
          "avg_corners_away_per_game": 4.0,
          "aproveitamento_away": 8.3,
          "over_2_5_goals_away": 2,
          "over_0_5_ht_away": 2,
          "over_0_5_ft_away": 1,
          "clean_sheets_away": 0
        },
        "update": "2025-09-23T00:00:00+00:00"
      },
      {
        "rank": 9,
        "team": {
          "id": 625,
          "name": "CR Vasco da Gama",
          "logo": "https://cdn.footystats.org/img/teams/brazil-cr-vasco-da-gama.png"
        },
        "points": 11,
        "goalsDiff": 0,
        "group": "Brazil Serie A 2026",
        "status": "same",
        "description": "",
        "all": {
          "played": 8,
          "win": 3,
          "draw": 2,
          "lose": 3,
          "goals": {
            "for": 13,
            "against": 13
          },
          "form": "LWDWW",
          "btts_matches": 7,
          "avg_corners_per_game": 5.88,
          "aproveitamento": 45.8,
          "over_2_5_goals": 6,
          "over_0_5_ht": 3,
          "over_0_5_ft": 4,
          "clean_sheets": 0
        },
        "home": {
          "played": 5,
          "win": 3,
          "draw": 1,
          "lose": 1,
          "goals": {
            "for": 8,
            "against": 6
          },
          "form_home": "DLWWW",
          "avg_corners_home_per_game": 7.2,
          "aproveitamento_home": 66.7,
          "btts_home_matches": 4,
          "over_2_5_goals_home": 3,
          "over_0_5_ht_home": 1,
          "over_0_5_ft_home": 3,
          "clean_sheets_home": 0
        },
        "away": {
          "played": 3,
          "win": 0,
          "draw": 1,
          "lose": 2,
          "goals": {
            "for": 5,
            "against": 7
          },
          "form_visitor": "LLD",
          "btts_away_matches": 3,
          "avg_corners_away_per_game": 3.67,
          "aproveitamento_away": 11.1,
          "over_2_5_goals_away": 3,
          "over_0_5_ht_away": 2,
          "over_0_5_ft_away": 1,
          "clean_sheets_away": 0
        },
        "update": "2025-09-23T00:00:00+00:00"
      },
      {
        "rank": 10,
        "team": {
          "id": 610,
          "name": "EC Vitória",
          "logo": "https://cdn.footystats.org/img/teams/brazil-ec-vitoria.png"
        },
        "points": 10,
        "goalsDiff": -2,
        "group": "Brazil Serie A 2026",
        "status": "same",
        "description": "",
        "all": {
          "played": 7,
          "win": 3,
          "draw": 1,
          "lose": 3,
          "goals": {
            "for": 8,
            "against": 10
          },
          "form": "LDWLW",
          "btts_matches": 3,
          "avg_corners_per_game": 4.43,
          "aproveitamento": 47.6,
          "over_2_5_goals": 2,
          "over_0_5_ht": 3,
          "over_0_5_ft": 4,
          "clean_sheets": 3
        },
        "home": {
          "played": 4,
          "win": 3,
          "draw": 0,
          "lose": 1,
          "goals": {
            "for": 6,
            "against": 2
          },
          "form_home": "WLWW",
          "avg_corners_home_per_game": 4.75,
          "aproveitamento_home": 75.0,
          "btts_home_matches": 1,
          "over_2_5_goals_home": 1,
          "over_0_5_ht_home": 2,
          "over_0_5_ft_home": 3,
          "clean_sheets_home": 3
        },
        "away": {
          "played": 3,
          "win": 0,
          "draw": 1,
          "lose": 2,
          "goals": {
            "for": 2,
            "against": 8
          },
          "form_visitor": "LDL",
          "btts_away_matches": 2,
          "avg_corners_away_per_game": 4.0,
          "aproveitamento_away": 11.1,
          "over_2_5_goals_away": 1,
          "over_0_5_ht_away": 1,
          "over_0_5_ft_away": 1,
          "clean_sheets_away": 0
        },
        "update": "2025-09-23T00:00:00+00:00"
      },
      {
        "rank": 11,
        "team": {
          "id": 624,
          "name": "SC Corinthians Paulista",
          "logo": "https://cdn.footystats.org/img/teams/brazil-sc-corinthians-paulista.png"
        },
        "points": 10,
        "goalsDiff": 0,
        "group": "Brazil Serie A 2026",
        "status": "same",
        "description": "",
        "all": {
          "played": 8,
          "win": 2,
          "draw": 4,
          "lose": 2,
          "goals": {
            "for": 7,
            "against": 7
          },
          "form": "DLDDD",
          "btts_matches": 4,
          "avg_corners_per_game": 4.25,
          "aproveitamento": 41.7,
          "over_2_5_goals": 1,
          "over_0_5_ht": 4,
          "over_0_5_ft": 2,
          "clean_sheets": 3
        },
        "home": {
          "played": 4,
          "win": 1,
          "draw": 1,
          "lose": 2,
          "goals": {
            "for": 4,
            "against": 5
          },
          "form_home": "LWLD",
          "avg_corners_home_per_game": 5.25,
          "aproveitamento_home": 33.3,
          "btts_home_matches": 2,
          "over_2_5_goals_home": 1,
          "over_0_5_ht_home": 2,
          "over_0_5_ft_home": 1,
          "clean_sheets_home": 1
        },
        "away": {
          "played": 4,
          "win": 1,
          "draw": 3,
          "lose": 0,
          "goals": {
            "for": 3,
            "against": 2
          },
          "form_visitor": "WDDD",
          "btts_away_matches": 2,
          "avg_corners_away_per_game": 3.25,
          "aproveitamento_away": 50.0,
          "over_2_5_goals_away": 0,
          "over_0_5_ht_away": 2,
          "over_0_5_ft_away": 1,
          "clean_sheets_away": 2
        },
        "update": "2025-09-23T00:00:00+00:00"
      },
      {
        "rank": 12,
        "team": {
          "id": 630,
          "name": "SC Internacional",
          "logo": "https://cdn.footystats.org/img/teams/brazil-sc-internacional.png"
        },
        "points": 8,
        "goalsDiff": -2,
        "group": "Brazil Serie A 2026",
        "status": "same",
        "description": "",
        "all": {
          "played": 8,
          "win": 2,
          "draw": 2,
          "lose": 4,
          "goals": {
            "for": 7,
            "against": 9
          },
          "form": "DLLWW",
          "btts_matches": 4,
          "avg_corners_per_game": 9.62,
          "aproveitamento": 33.3,
          "over_2_5_goals": 2,
          "over_0_5_ht": 4,
          "over_0_5_ft": 2,
          "clean_sheets": 1
        },
        "home": {
          "played": 4,
          "win": 1,
          "draw": 0,
          "lose": 3,
          "goals": {
            "for": 3,
            "against": 5
          },
          "form_home": "LLLW",
          "avg_corners_home_per_game": 10.0,
          "aproveitamento_home": 25.0,
          "btts_home_matches": 1,
          "over_2_5_goals_home": 1,
          "over_0_5_ht_home": 2,
          "over_0_5_ft_home": 1,
          "clean_sheets_home": 1
        },
        "away": {
          "played": 4,
          "win": 1,
          "draw": 2,
          "lose": 1,
          "goals": {
            "for": 4,
            "against": 4
          },
          "form_visitor": "DDLW",
          "btts_away_matches": 3,
          "avg_corners_away_per_game": 9.25,
          "aproveitamento_away": 41.7,
          "over_2_5_goals_away": 1,
          "over_0_5_ht_away": 2,
          "over_0_5_ft_away": 1,
          "clean_sheets_away": 0
        },
        "update": "2025-09-23T00:00:00+00:00"
      },
      {
        "rank": 13,
        "team": {
          "id": 620,
          "name": "CA Mineiro",
          "logo": "https://cdn.footystats.org/img/teams/brazil-ca-mineiro.png"
        },
        "points": 8,
        "goalsDiff": -3,
        "group": "Brazil Serie A 2026",
        "status": "same",
        "description": "",
        "all": {
          "played": 8,
          "win": 2,
          "draw": 2,
          "lose": 4,
          "goals": {
            "for": 8,
            "against": 11
          },
          "form": "LWLWL",
          "btts_matches": 3,
          "avg_corners_per_game": 5.5,
          "aproveitamento": 33.3,
          "over_2_5_goals": 3,
          "over_0_5_ht": 3,
          "over_0_5_ft": 4,
          "clean_sheets": 2
        },
        "home": {
          "played": 4,
          "win": 2,
          "draw": 2,
          "lose": 0,
          "goals": {
            "for": 7,
            "against": 5
          },
          "form_home": "DDWW",
          "avg_corners_home_per_game": 4.25,
          "aproveitamento_home": 66.7,
          "btts_home_matches": 2,
          "over_2_5_goals_home": 2,
          "over_0_5_ht_home": 3,
          "over_0_5_ft_home": 3,
          "clean_sheets_home": 2
        },
        "away": {
          "played": 4,
          "win": 0,
          "draw": 0,
          "lose": 4,
          "goals": {
            "for": 1,
            "against": 6
          },
          "form_visitor": "LLLL",
          "btts_away_matches": 1,
          "avg_corners_away_per_game": 6.75,
          "aproveitamento_away": 0.0,
          "over_2_5_goals_away": 1,
          "over_0_5_ht_away": 0,
          "over_0_5_ft_away": 1,
          "clean_sheets_away": 0
        },
        "update": "2025-09-23T00:00:00+00:00"
      },
      {
        "rank": 14,
        "team": {
          "id": 635,
          "name": "Clube Atlético Bragantino",
          "logo": "https://cdn.footystats.org/img/teams/brazil-clube-atletico-bragantino.png"
        },
        "points": 8,
        "goalsDiff": -4,
        "group": "Brazil Serie A 2026",
        "status": "same",
        "description": "",
        "all": {
          "played": 8,
          "win": 2,
          "draw": 2,
          "lose": 4,
          "goals": {
            "for": 6,
            "against": 10
          },
          "form": "DDLLL",
          "btts_matches": 4,
          "avg_corners_per_game": 5.75,
          "aproveitamento": 33.3,
          "over_2_5_goals": 2,
          "over_0_5_ht": 4,
          "over_0_5_ft": 2,
          "clean_sheets": 2
        },
        "home": {
          "played": 4,
          "win": 1,
          "draw": 1,
          "lose": 2,
          "goals": {
            "for": 4,
            "against": 5
          },
          "form_home": "WDLL",
          "avg_corners_home_per_game": 6.25,
          "aproveitamento_home": 33.3,
          "btts_home_matches": 3,
          "over_2_5_goals_home": 2,
          "over_0_5_ht_home": 4,
          "over_0_5_ft_home": 0,
          "clean_sheets_home": 1
        },
        "away": {
          "played": 4,
          "win": 1,
          "draw": 1,
          "lose": 2,
          "goals": {
            "for": 2,
            "against": 5
          },
          "form_visitor": "WLDL",
          "btts_away_matches": 1,
          "avg_corners_away_per_game": 5.25,
          "aproveitamento_away": 33.3,
          "over_2_5_goals_away": 0,
          "over_0_5_ht_away": 0,
          "over_0_5_ft_away": 2,
          "clean_sheets_away": 1
        },
        "update": "2025-09-23T00:00:00+00:00"
      },
      {
        "rank": 15,
        "team": {
          "id": 623,
          "name": "Chapecoense AF",
          "logo": "https://cdn.footystats.org/img/teams/brazil-chapecoense-af.png"
        },
        "points": 7,
        "goalsDiff": -2,
        "group": "Brazil Serie A 2026",
        "status": "same",
        "description": "",
        "all": {
          "played": 7,
          "win": 1,
          "draw": 4,
          "lose": 2,
          "goals": {
            "for": 9,
            "against": 11
          },
          "form": "DLDDL",
          "btts_matches": 4,
          "avg_corners_per_game": 3.86,
          "aproveitamento": 33.3,
          "over_2_5_goals": 2,
          "over_0_5_ht": 3,
          "over_0_5_ft": 3,
          "clean_sheets": 1
        },
        "home": {
          "played": 4,
          "win": 1,
          "draw": 3,
          "lose": 0,
          "goals": {
            "for": 8,
            "against": 6
          },
          "form_home": "WDDD",
          "avg_corners_home_per_game": 4.25,
          "aproveitamento_home": 50.0,
          "btts_home_matches": 3,
          "over_2_5_goals_home": 2,
          "over_0_5_ht_home": 3,
          "over_0_5_ft_home": 2,
          "clean_sheets_home": 1
        },
        "away": {
          "played": 3,
          "win": 0,
          "draw": 1,
          "lose": 2,
          "goals": {
            "for": 1,
            "against": 5
          },
          "form_visitor": "DLL",
          "btts_away_matches": 1,
          "avg_corners_away_per_game": 3.33,
          "aproveitamento_away": 11.1,
          "over_2_5_goals_away": 0,
          "over_0_5_ht_away": 0,
          "over_0_5_ft_away": 1,
          "clean_sheets_away": 0
        },
        "update": "2025-09-23T00:00:00+00:00"
      },
      {
        "rank": 16,
        "team": {
          "id": 611,
          "name": "Santos FC Sao Paulo",
          "logo": "https://cdn.footystats.org/img/teams/brazil-santos-fc-sao-paulo.png"
        },
        "points": 7,
        "goalsDiff": -3,
        "group": "Brazil Serie A 2026",
        "status": "same",
        "description": "",
        "all": {
          "played": 8,
          "win": 1,
          "draw": 4,
          "lose": 3,
          "goals": {
            "for": 10,
            "against": 13
          },
          "form": "WDDLD",
          "btts_matches": 7,
          "avg_corners_per_game": 5.25,
          "aproveitamento": 29.2,
          "over_2_5_goals": 5,
          "over_0_5_ht": 5,
          "over_0_5_ft": 4,
          "clean_sheets": 1
        },
        "home": {
          "played": 4,
          "win": 1,
          "draw": 2,
          "lose": 1,
          "goals": {
            "for": 5,
            "against": 5
          },
          "form_home": "DWDL",
          "avg_corners_home_per_game": 4.75,
          "aproveitamento_home": 41.7,
          "btts_home_matches": 4,
          "over_2_5_goals_home": 2,
          "over_0_5_ht_home": 3,
          "over_0_5_ft_home": 2,
          "clean_sheets_home": 0
        },
        "away": {
          "played": 4,
          "win": 0,
          "draw": 2,
          "lose": 2,
          "goals": {
            "for": 5,
            "against": 8
          },
          "form_visitor": "LLDD",
          "btts_away_matches": 3,
          "avg_corners_away_per_game": 5.75,
          "aproveitamento_away": 16.7,
          "over_2_5_goals_away": 3,
          "over_0_5_ht_away": 2,
          "over_0_5_ft_away": 2,
          "clean_sheets_away": 1
        },
        "update": "2025-09-23T00:00:00+00:00"
      },
      {
        "rank": 17,
        "team": {
          "id": 615,
          "name": "Botafogo FR",
          "logo": "https://cdn.footystats.org/img/teams/brazil-botafogo-fr.png"
        },
        "points": 6,
        "goalsDiff": -2,
        "group": "Brazil Serie A 2026",
        "status": "same",
        "description": "Rebaixamento",
        "all": {
          "played": 6,
          "win": 2,
          "draw": 0,
          "lose": 4,
          "goals": {
            "for": 10,
            "against": 12
          },
          "form": "LLLLW",
          "btts_matches": 3,
          "avg_corners_per_game": 2.33,
          "aproveitamento": 33.3,
          "over_2_5_goals": 5,
          "over_0_5_ht": 2,
          "over_0_5_ft": 4,
          "clean_sheets": 1
        },
        "home": {
          "played": 2,
          "win": 1,
          "draw": 0,
          "lose": 1,
          "goals": {
            "for": 4,
            "against": 3
          },
          "form_home": "WL",
          "avg_corners_home_per_game": 2.5,
          "aproveitamento_home": 50.0,
          "btts_home_matches": 0,
          "over_2_5_goals_home": 2,
          "over_0_5_ht_home": 0,
          "over_0_5_ft_home": 1,
          "clean_sheets_home": 1
        },
        "away": {
          "played": 4,
          "win": 1,
          "draw": 0,
          "lose": 3,
          "goals": {
            "for": 6,
            "against": 9
          },
          "form_visitor": "LLLW",
          "btts_away_matches": 3,
          "avg_corners_away_per_game": 2.25,
          "aproveitamento_away": 25.0,
          "over_2_5_goals_away": 3,
          "over_0_5_ht_away": 2,
          "over_0_5_ft_away": 3,
          "clean_sheets_away": 0
        },
        "update": "2025-09-23T00:00:00+00:00"
      },
      {
        "rank": 18,
        "team": {
          "id": 2721,
          "name": "Mirassol Futebol Clube",
          "logo": "https://cdn.footystats.org/img/teams/brazil-mirassol-futebol-clube.png"
        },
        "points": 6,
        "goalsDiff": -2,
        "group": "Brazil Serie A 2026",
        "status": "same",
        "description": "Rebaixamento",
        "all": {
          "played": 7,
          "win": 1,
          "draw": 3,
          "lose": 3,
          "goals": {
            "for": 8,
            "against": 10
          },
          "form": "DDLLL",
          "btts_matches": 4,
          "avg_corners_per_game": 5.71,
          "aproveitamento": 28.6,
          "over_2_5_goals": 4,
          "over_0_5_ht": 3,
          "over_0_5_ft": 4,
          "clean_sheets": 0
        },
        "home": {
          "played": 4,
          "win": 1,
          "draw": 2,
          "lose": 1,
          "goals": {
            "for": 6,
            "against": 6
          },
          "form_home": "WDDL",
          "avg_corners_home_per_game": 6.75,
          "aproveitamento_home": 41.7,
          "btts_home_matches": 3,
          "over_2_5_goals_home": 3,
          "over_0_5_ht_home": 3,
          "over_0_5_ft_home": 3,
          "clean_sheets_home": 0
        },
        "away": {
          "played": 3,
          "win": 0,
          "draw": 1,
          "lose": 2,
          "goals": {
            "for": 2,
            "against": 4
          },
          "form_visitor": "DLL",
          "btts_away_matches": 1,
          "avg_corners_away_per_game": 4.33,
          "aproveitamento_away": 11.1,
          "over_2_5_goals_away": 1,
          "over_0_5_ht_away": 0,
          "over_0_5_ft_away": 1,
          "clean_sheets_away": 0
        },
        "update": "2025-09-23T00:00:00+00:00"
      },
      {
        "rank": 19,
        "team": {
          "id": 2594,
          "name": "Clube do Remo",
          "logo": "https://cdn.footystats.org/img/teams/brazil-clube-do-remo.png"
        },
        "points": 6,
        "goalsDiff": -5,
        "group": "Brazil Serie A 2026",
        "status": "same",
        "description": "Rebaixamento",
        "all": {
          "played": 8,
          "win": 1,
          "draw": 3,
          "lose": 4,
          "goals": {
            "for": 10,
            "against": 15
          },
          "form": "DLLLW",
          "btts_matches": 4,
          "avg_corners_per_game": 4.5,
          "aproveitamento": 25.0,
          "over_2_5_goals": 4,
          "over_0_5_ht": 4,
          "over_0_5_ft": 2,
          "clean_sheets": 0
        },
        "home": {
          "played": 4,
          "win": 1,
          "draw": 2,
          "lose": 1,
          "goals": {
            "for": 7,
            "against": 6
          },
          "form_home": "DDLW",
          "avg_corners_home_per_game": 5.5,
          "aproveitamento_home": 41.7,
          "btts_home_matches": 3,
          "over_2_5_goals_home": 2,
          "over_0_5_ht_home": 3,
          "over_0_5_ft_home": 1,
          "clean_sheets_home": 0
        },
        "away": {
          "played": 4,
          "win": 0,
          "draw": 1,
          "lose": 3,
          "goals": {
            "for": 3,
            "against": 9
          },
          "form_visitor": "LDLL",
          "btts_away_matches": 1,
          "avg_corners_away_per_game": 3.5,
          "aproveitamento_away": 8.3,
          "over_2_5_goals_away": 2,
          "over_0_5_ht_away": 1,
          "over_0_5_ft_away": 1,
          "clean_sheets_away": 0
        },
        "update": "2025-09-23T00:00:00+00:00"
      },
      {
        "rank": 20,
        "team": {
          "id": 613,
          "name": "Cruzeiro EC",
          "logo": "https://cdn.footystats.org/img/teams/brazil-cruzeiro-ec.png"
        },
        "points": 4,
        "goalsDiff": -8,
        "group": "Brazil Serie A 2026",
        "status": "same",
        "description": "Rebaixamento",
        "all": {
          "played": 8,
          "win": 0,
          "draw": 4,
          "lose": 4,
          "goals": {
            "for": 8,
            "against": 16
          },
          "form": "DLDLD",
          "btts_matches": 5,
          "avg_corners_per_game": 6.0,
          "aproveitamento": 16.7,
          "over_2_5_goals": 5,
          "over_0_5_ht": 4,
          "over_0_5_ft": 3,
          "clean_sheets": 1
        },
        "home": {
          "played": 4,
          "win": 0,
          "draw": 3,
          "lose": 1,
          "goals": {
            "for": 5,
            "against": 6
          },
          "form_home": "LDDD",
          "avg_corners_home_per_game": 7.0,
          "aproveitamento_home": 25.0,
          "btts_home_matches": 3,
          "over_2_5_goals_home": 2,
          "over_0_5_ht_home": 3,
          "over_0_5_ft_home": 1,
          "clean_sheets_home": 1
        },
        "away": {
          "played": 4,
          "win": 0,
          "draw": 1,
          "lose": 3,
          "goals": {
            "for": 3,
            "against": 10
          },
          "form_visitor": "LDLL",
          "btts_away_matches": 2,
          "avg_corners_away_per_game": 5.0,
          "aproveitamento_away": 8.3,
          "over_2_5_goals_away": 3,
          "over_0_5_ht_away": 1,
          "over_0_5_ft_away": 2,
          "clean_sheets_away": 0
        },
        "update": "2025-09-23T00:00:00+00:00"
      }
    ]
  },
  "artilharia": {
    "brazil_serie_a": [
      {
        "jogador-nome": "Carlos Vinícius Alves Morais",
        "jogador-posicao": "Forward",
        "jogador-gols": 6,
        "jogador-assists": 0,
        "jogador-partidas": 8,
        "jogador-escudo": "https://cdn.footystats.org/img/teams/brazil-gremio-fb-porto-alegrense.png",
        "jogador-foto": "https://cdn.footystats.org/img/players/brazil-carlos-vinicius.png"
      },
      {
        "jogador-nome": "Danilo dos Santos de Oliveira",
        "jogador-posicao": "Midfielder",
        "jogador-gols": 5,
        "jogador-assists": 1,
        "jogador-partidas": 6,
        "jogador-escudo": "https://cdn.footystats.org/img/teams/brazil-botafogo-fr.png",
        "jogador-foto": "https://cdn.footystats.org/img/players/brazil-danilo-oliveira.png"
      },
      {
        "jogador-nome": "Jonathan Calleri",
        "jogador-posicao": "Forward",
        "jogador-gols": 4,
        "jogador-assists": 0,
        "jogador-partidas": 8,
        "jogador-escudo": "https://cdn.footystats.org/img/teams/brazil-sao-paulo-fc.png",
        "jogador-foto": "https://cdn.footystats.org/img/players/argentina-jonathan-calleri.png"
      },
      {
        "jogador-nome": "Luciano Federico Acosta",
        "jogador-posicao": "Midfielder",
        "jogador-gols": 3,
        "jogador-assists": 3,
        "jogador-partidas": 8,
        "jogador-escudo": "https://cdn.footystats.org/img/teams/brazil-fluminense-fc.png",
        "jogador-foto": "https://cdn.footystats.org/img/players/argentina-luciano-acosta.png"
      },
      {
        "jogador-nome": "José Manuel López",
        "jogador-posicao": "Forward",
        "jogador-gols": 3,
        "jogador-assists": 2,
        "jogador-partidas": 8,
        "jogador-escudo": "https://cdn.footystats.org/img/teams/brazil-se-palmeiras.png",
        "jogador-foto": "https://cdn.footystats.org/img/players/argentina-jose-manuel-lopez.png"
      },
      {
        "jogador-nome": "Walter David Clar Fritz",
        "jogador-posicao": "Midfielder",
        "jogador-gols": 3,
        "jogador-assists": 1,
        "jogador-partidas": 7,
        "jogador-escudo": "https://cdn.footystats.org/img/teams/brazil-chapecoense-af.png",
        "jogador-foto": "https://cdn.footystats.org/img/players/paraguay-walter-david-clar-fritz.png"
      },
      {
        "jogador-nome": "Neymar da Silva Santos Junior",
        "jogador-posicao": "Forward",
        "jogador-gols": 3,
        "jogador-assists": 1,
        "jogador-partidas": 3,
        "jogador-escudo": "https://cdn.footystats.org/img/teams/brazil-santos-fc-sao-paulo.png",
        "jogador-foto": "https://cdn.footystats.org/img/players/brazil-neymar.png"
      },
      {
        "jogador-nome": "Kevin Stiven Viveros Rodallega",
        "jogador-posicao": "Forward",
        "jogador-gols": 3,
        "jogador-assists": 1,
        "jogador-partidas": 7,
        "jogador-escudo": "https://cdn.footystats.org/img/teams/brazil-ca-paranaense.png",
        "jogador-foto": "https://cdn.footystats.org/img/players/colombia-kevin-stiven-viveros-rodallega.png"
      },
      {
        "jogador-nome": "Breno Henrique Vaconcelos Lopes",
        "jogador-posicao": "Forward",
        "jogador-gols": 3,
        "jogador-assists": 1,
        "jogador-partidas": 8,
        "jogador-escudo": "https://cdn.footystats.org/img/teams/brazil-coritiba-fbc.png",
        "jogador-foto": "https://cdn.footystats.org/img/players/brazil-breno-lopes.png"
      },
      {
        "jogador-nome": "Agustín Canobbio Graviz",
        "jogador-posicao": "Midfielder",
        "jogador-gols": 3,
        "jogador-assists": 1,
        "jogador-partidas": 7,
        "jogador-escudo": "https://cdn.footystats.org/img/teams/brazil-fluminense-fc.png",
        "jogador-foto": "https://cdn.footystats.org/img/players/uruguay-agustin-canobbio-graviz.png"
      },
      {
        "jogador-nome": "Vitor Hugo Roque Ferreira",
        "jogador-posicao": "Forward",
        "jogador-gols": 3,
        "jogador-assists": 0,
        "jogador-partidas": 6,
        "jogador-escudo": "https://cdn.footystats.org/img/teams/brazil-se-palmeiras.png",
        "jogador-foto": "https://cdn.footystats.org/img/players/brazil-vitor-roque.png"
      },
      {
        "jogador-nome": "John Stiven Mendoza Valencia",
        "jogador-posicao": "Forward",
        "jogador-gols": 3,
        "jogador-assists": 0,
        "jogador-partidas": 7,
        "jogador-escudo": "https://cdn.footystats.org/img/teams/brazil-ca-paranaense.png",
        "jogador-foto": "https://cdn.footystats.org/img/players/colombia-john-stiven-mendoza-valencia.png"
      },
      {
        "jogador-nome": "Gabriel Barbosa Almeida",
        "jogador-posicao": "Forward",
        "jogador-gols": 3,
        "jogador-assists": 0,
        "jogador-partidas": 4,
        "jogador-escudo": "https://cdn.footystats.org/img/teams/brazil-santos-fc-sao-paulo.png",
        "jogador-foto": "https://cdn.footystats.org/img/players/brazil-gabriel-barbosa-almeida.png"
      },
      {
        "jogador-nome": "Cauan Lucas Barros da Luz",
        "jogador-posicao": "Midfielder",
        "jogador-gols": 3,
        "jogador-assists": 0,
        "jogador-partidas": 6,
        "jogador-escudo": "https://cdn.footystats.org/img/teams/brazil-cr-vasco-da-gama.png",
        "jogador-foto": "https://cdn.footystats.org/img/players/-cauan-lucas-barros-da-luz.png"
      },
      {
        "jogador-nome": "Allan Andrade Elias",
        "jogador-posicao": "Midfielder",
        "jogador-gols": 3,
        "jogador-assists": 0,
        "jogador-partidas": 8,
        "jogador-escudo": "https://cdn.footystats.org/img/teams/brazil-se-palmeiras.png",
        "jogador-foto": "https://cdn.footystats.org/img/players/-allan-andrade-elias.png"
      },
      {
        "jogador-nome": "Luis Eduardo Soares da Silva",
        "jogador-posicao": "Defender",
        "jogador-gols": 2,
        "jogador-assists": 3,
        "jogador-partidas": 5,
        "jogador-escudo": "https://cdn.footystats.org/img/teams/brazil-cr-vasco-da-gama.png",
        "jogador-foto": "https://cdn.footystats.org/img/players/-luis-eduardo-soares-da-silva.png"
      },
      {
        "jogador-nome": "Alef Mangueira Severino Pereira",
        "jogador-posicao": "Forward",
        "jogador-gols": 2,
        "jogador-assists": 3,
        "jogador-partidas": 8,
        "jogador-escudo": "https://cdn.footystats.org/img/teams/brazil-clube-do-remo.png",
        "jogador-foto": "https://cdn.footystats.org/img/players/brazil-alef-mangueira-severino-pereira.png"
      },
      {
        "jogador-nome": "Pedro Guilherme Abreu dos Santos",
        "jogador-posicao": "Forward",
        "jogador-gols": 2,
        "jogador-assists": 2,
        "jogador-partidas": 7,
        "jogador-escudo": "https://cdn.footystats.org/img/teams/brazil-cr-flamengo.png",
        "jogador-foto": "https://cdn.footystats.org/img/players/brazil-pedro-guilherme-abreu-dos-santos.png"
      },
      {
        "jogador-nome": "Jean Carlos Vicente",
        "jogador-posicao": "Midfielder",
        "jogador-gols": 2,
        "jogador-assists": 2,
        "jogador-partidas": 7,
        "jogador-escudo": "https://cdn.footystats.org/img/teams/brazil-chapecoense-af.png",
        "jogador-foto": "https://cdn.footystats.org/img/players/brazil-jean-carlos-vicente.png"
      },
      {
        "jogador-nome": "Gabriel Baralhas dos Santos",
        "jogador-posicao": "Midfielder",
        "jogador-gols": 2,
        "jogador-assists": 2,
        "jogador-partidas": 7,
        "jogador-escudo": "https://cdn.footystats.org/img/teams/brazil-ec-vitoria.png",
        "jogador-foto": "https://cdn.footystats.org/img/players/brazil-gabriel-baralhas.png"
      }
    ]
  }
}