{
  "standings": {
    "international_wc_qualification_oceania": [
      {
        "rank": 1,
        "team": {
          "id": 8697,
          "name": "New Zealand National Team",
          "logo": "https://cdn.footystats.org/img/teams/new-zealand-new-zealand-national-team.png"
        },
        "points": 15,
        "goalsDiff": 28,
        "group": "International WC Qualification Oceania 2026",
        "status": "same",
        "description": "Copa Libertadores",
        "all": {
          "played": 5,
          "win": 5,
          "draw": 0,
          "lose": 0,
          "goals": {
            "for": 29,
            "against": 1
          },
          "form": "WWWWW",
          "btts_matches": 1,
          "avg_corners_per_game": 4.4,
          "aproveitamento": 100.0,
          "over_2_5_goals": 5,
          "over_0_5_ht": 4,
          "over_0_5_ft": 5,
          "clean_sheets": 4
        },
        "home": {
          "played": 3,
          "win": 3,
          "draw": 0,
          "lose": 0,
          "goals": {
            "for": 18,
            "against": 1
          },
          "form_home": "WWW",
          "avg_corners_home_per_game": 1.33,
          "aproveitamento_home": 100.0,
          "btts_home_matches": 1,
          "over_2_5_goals_home": 3,
          "over_0_5_ht_home": 3,
          "over_0_5_ft_home": 3,
          "clean_sheets_home": 2
        },
        "away": {
          "played": 2,
          "win": 2,
          "draw": 0,
          "lose": 0,
          "goals": {
            "for": 11,
            "against": 0
          },
          "form_visitor": "WW",
          "btts_away_matches": 0,
          "avg_corners_away_per_game": 9.0,
          "aproveitamento_away": 100.0,
          "over_2_5_goals_away": 2,
          "over_0_5_ht_away": 1,
          "over_0_5_ft_away": 2,
          "clean_sheets_away": 2
        },
        "update": "2025-09-23T00:00:00+00:00"
      },
      {
        "rank": 2,
        "team": {
          "id": 8700,
          "name": "New Caledonia National Team",
          "logo": "https://cdn.footystats.org/img/teams/new-caledonia-new-caledonia-national-team.png"
        },
        "points": 10,
        "goalsDiff": 3,
        "group": "International WC Qualification Oceania 2026",
        "status": "same",
        "description": "Copa Libertadores",
        "all": {
          "played": 5,
          "win": 3,
          "draw": 1,
          "lose": 1,
          "goals": {
            "for": 10,
            "against": 7
          },
          "form": "WWDWL",
          "btts_matches": 3,
          "avg_corners_per_game": 2.2,
          "aproveitamento": 66.7,
          "over_2_5_goals": 4,
          "over_0_5_ht": 2,
          "over_0_5_ft": 4,
          "clean_sheets": 1
        },
        "home": {
          "played": 3,
          "win": 2,
          "draw": 0,
          "lose": 1,
          "goals": {
            "for": 6,
            "against": 4
          },
          "form_home": "WWL",
          "avg_corners_home_per_game": 4.33,
          "aproveitamento_home": 66.7,
          "btts_home_matches": 1,
          "over_2_5_goals_home": 3,
          "over_0_5_ht_home": 1,
          "over_0_5_ft_home": 2,
          "clean_sheets_home": 1
        },
        "away": {
          "played": 2,
          "win": 1,
          "draw": 1,
          "lose": 0,
          "goals": {
            "for": 4,
            "against": 3
          },
          "form_visitor": "WD",
          "btts_away_matches": 2,
          "avg_corners_away_per_game": -1.0,
          "aproveitamento_away": 66.7,
          "over_2_5_goals_away": 1,
          "over_0_5_ht_away": 1,
          "over_0_5_ft_away": 2,
          "clean_sheets_away": 0
        },
        "update": "2025-09-23T00:00:00+00:00"
      },
      {
        "rank": 3,
        "team": {
          "id": 8672,
          "name": "Tahiti National Team",
          "logo": "https://cdn.footystats.org/img/teams/tahiti-tahiti-national-team.png"
        },
        "points": 6,
        "goalsDiff": -1,
        "group": "International WC Qualification Oceania 2026",
        "status": "same",
        "description": "Copa Libertadores",
        "all": {
          "played": 4,
          "win": 2,
          "draw": 0,
          "lose": 2,
          "goals": {
            "for": 5,
            "against": 6
          },
          "form": "LWWL",
          "btts_matches": 0,
          "avg_corners_per_game": 2.5,
          "aproveitamento": 50.0,
          "over_2_5_goals": 3,
          "over_0_5_ht": 1,
          "over_0_5_ft": 2,
          "clean_sheets": 2
        },
        "home": {
          "played": 1,
          "win": 1,
          "draw": 0,
          "lose": 0,
          "goals": {
            "for": 2,
            "against": 0
          },
          "form_home": "W",
          "avg_corners_home_per_game": 4.0,
          "aproveitamento_home": 100.0,
          "btts_home_matches": 0,
          "over_2_5_goals_home": 0,
          "over_0_5_ht_home": 1,
          "over_0_5_ft_home": 1,
          "clean_sheets_home": 1
        },
        "away": {
          "played": 3,
          "win": 1,
          "draw": 0,
          "lose": 2,
          "goals": {
            "for": 3,
            "against": 6
          },
          "form_visitor": "LWL",
          "btts_away_matches": 0,
          "avg_corners_away_per_game": 2.0,
          "aproveitamento_away": 33.3,
          "over_2_5_goals_away": 3,
          "over_0_5_ht_away": 0,
          "over_0_5_ft_away": 1,
          "clean_sheets_away": 1
        },
        "update": "2025-09-23T00:00:00+00:00"
      },
      {
        "rank": 4,
        "team": {
          "id": 1268200,
          "name": "Samoa",
          "logo": "https://cdn.footystats.org/img/teams/samoa-samoa.png"
        },
        "points": 6,
        "goalsDiff": -11,
        "group": "International WC Qualification Oceania 2026",
        "status": "same",
        "description": "Copa Libertadores",
        "all": {
          "played": 5,
          "win": 2,
          "draw": 0,
          "lose": 3,
          "goals": {
            "for": 5,
            "against": 16
          },
          "form": "WWLLL",
          "btts_matches": 2,
          "avg_corners_per_game": 0.2,
          "aproveitamento": 40.0,
          "over_2_5_goals": 4,
          "over_0_5_ht": 0,
          "over_0_5_ft": 3,
          "clean_sheets": 1
        },
        "home": {
          "played": 2,
          "win": 0,
          "draw": 0,
          "lose": 2,
          "goals": {
            "for": 0,
            "against": 11
          },
          "form_home": "LL",
          "avg_corners_home_per_game": 2.0,
          "aproveitamento_home": 0.0,
          "btts_home_matches": 0,
          "over_2_5_goals_home": 2,
          "over_0_5_ht_home": 0,
          "over_0_5_ft_home": 0,
          "clean_sheets_home": 0
        },
        "away": {
          "played": 3,
          "win": 2,
          "draw": 0,
          "lose": 1,
          "goals": {
            "for": 5,
            "against": 5
          },
          "form_visitor": "WWL",
          "btts_away_matches": 2,
          "avg_corners_away_per_game": -1.0,
          "aproveitamento_away": 66.7,
          "over_2_5_goals_away": 2,
          "over_0_5_ht_away": 0,
          "over_0_5_ft_away": 3,
          "clean_sheets_away": 1
        },
        "update": "2025-09-23T00:00:00+00:00"
      },
      {
        "rank": 5,
        "team": {
          "id": 8705,
          "name": "Fiji National Team",
          "logo": "https://cdn.footystats.org/img/teams/fiji-fiji-national-team.png"
        },
        "points": 5,
        "goalsDiff": -6,
        "group": "International WC Qualification Oceania 2026",
        "status": "same",
        "description": "Copa Sul-Americana",
        "all": {
          "played": 4,
          "win": 1,
          "draw": 2,
          "lose": 1,
          "goals": {
            "for": 5,
            "against": 11
          },
          "form": "WDDL",
          "btts_matches": 2,
          "avg_corners_per_game": 1.25,
          "aproveitamento": 41.7,
          "over_2_5_goals": 2,
          "over_0_5_ht": 3,
          "over_0_5_ft": 1,
          "clean_sheets": 1
        },
        "home": {
          "played": 1,
          "win": 0,
          "draw": 1,
          "lose": 0,
          "goals": {
            "for": 1,
            "against": 1
          },
          "form_home": "D",
          "avg_corners_home_per_game": -1.0,
          "aproveitamento_home": 33.3,
          "btts_home_matches": 1,
          "over_2_5_goals_home": 0,
          "over_0_5_ht_home": 1,
          "over_0_5_ft_home": 0,
          "clean_sheets_home": 0
        },
        "away": {
          "played": 3,
          "win": 1,
          "draw": 1,
          "lose": 1,
          "goals": {
            "for": 4,
            "against": 10
          },
          "form_visitor": "WDL",
          "btts_away_matches": 1,
          "avg_corners_away_per_game": 2.0,
          "aproveitamento_away": 44.4,
          "over_2_5_goals_away": 2,
          "over_0_5_ht_away": 2,
          "over_0_5_ft_away": 1,
          "clean_sheets_away": 1
        },
        "update": "2025-09-23T00:00:00+00:00"
      },
      {
        "rank": 6,
        "team": {
          "id": 8735,
          "name": "Tonga National Team",
          "logo": "https://cdn.footystats.org/img/teams/tonga-tonga-national-team.png"
        },
        "points": 3,
        "goalsDiff": 1,
        "group": "International WC Qualification Oceania 2026",
        "status": "same",
        "description": "Copa Sul-Americana",
        "all": {
          "played": 2,
          "win": 1,
          "draw": 0,
          "lose": 1,
          "goals": {
            "for": 4,
            "against": 3
          },
          "form": "WL",
          "btts_matches": 2,
          "avg_corners_per_game": -1.0,
          "aproveitamento": 50.0,
          "over_2_5_goals": 2,
          "over_0_5_ht": 2,
          "over_0_5_ft": 1,
          "clean_sheets": 0
        },
        "home": {
          "played": 1,
          "win": 0,
          "draw": 0,
          "lose": 1,
          "goals": {
            "for": 1,
            "against": 2
          },
          "form_home": "L",
          "avg_corners_home_per_game": -1.0,
          "aproveitamento_home": 0.0,
          "btts_home_matches": 1,
          "over_2_5_goals_home": 1,
          "over_0_5_ht_home": 1,
          "over_0_5_ft_home": 0,
          "clean_sheets_home": 0
        },
        "away": {
          "played": 1,
          "win": 1,
          "draw": 0,
          "lose": 0,
          "goals": {
            "for": 3,
            "against": 1
          },
          "form_visitor": "W",
          "btts_away_matches": 1,
          "avg_corners_away_per_game": -1.0,
          "aproveitamento_away": 100.0,
          "over_2_5_goals_away": 1,
          "over_0_5_ht_away": 1,
          "over_0_5_ft_away": 1,
          "clean_sheets_away": 0
        },
        "update": "2025-09-23T00:00:00+00:00"
      },
      {
        "rank": 7,
        "team": {
          "id": 8728,
          "name": "Solomon Islands National Team",
          "logo": "https://cdn.footystats.org/img/teams/solomon-islands-solomon-islands-national-team.png"
        },
        "points": 3,
        "goalsDiff": -1,
        "group": "International WC Qualification Oceania 2026",
        "status": "same",
        "description": "",
        "all": {
          "played": 3,
          "win": 1,
          "draw": 0,
          "lose": 2,
          "goals": {
            "for": 4,
            "against": 5
          },
          "form": "LLW",
          "btts_matches": 2,
          "avg_corners_per_game": 1.0,
          "aproveitamento": 33.3,
          "over_2_5_goals": 2,
          "over_0_5_ht": 2,
          "over_0_5_ft": 1,
          "clean_sheets": 0
        },
        "home": {
          "played": 2,
          "win": 0,
          "draw": 0,
          "lose": 2,
          "goals": {
            "for": 2,
            "against": 4
          },
          "form_home": "LL",
          "avg_corners_home_per_game": 2.0,
          "aproveitamento_home": 0.0,
          "btts_home_matches": 1,
          "over_2_5_goals_home": 1,
          "over_0_5_ht_home": 1,
          "over_0_5_ft_home": 0,
          "clean_sheets_home": 0
        },
        "away": {
          "played": 1,
          "win": 1,
          "draw": 0,
          "lose": 0,
          "goals": {
            "for": 2,
            "against": 1
          },
          "form_visitor": "W",
          "btts_away_matches": 1,
          "avg_corners_away_per_game": -1.0,
          "aproveitamento_away": 100.0,
          "over_2_5_goals_away": 1,
          "over_0_5_ht_away": 1,
          "over_0_5_ft_away": 1,
          "clean_sheets_away": 0
        },
        "update": "2025-09-23T00:00:00+00:00"
      },
      {
        "rank": 8,
        "team": {
          "id": 8732,
          "name": "Vanuatu National Team",
          "logo": "https://cdn.footystats.org/img/teams/vanuatu-vanuatu-national-team.png"
        },
        "points": 3,
        "goalsDiff": -6,
        "group": "International WC Qualification Oceania 2026",
        "status": "same",
        "description": "",
        "all": {
          "played": 3,
          "win": 1,
          "draw": 0,
          "lose": 2,
          "goals": {
            "for": 5,
            "against": 11
          },
          "form": "WLL",
          "btts_matches": 2,
          "avg_corners_per_game": 1.67,
          "aproveitamento": 33.3,
          "over_2_5_goals": 2,
          "over_0_5_ht": 2,
          "over_0_5_ft": 1,
          "clean_sheets": 0
        },
        "home": {
          "played": 1,
          "win": 1,
          "draw": 0,
          "lose": 0,
          "goals": {
            "for": 4,
            "against": 1
          },
          "form_home": "W",
          "avg_corners_home_per_game": -1.0,
          "aproveitamento_home": 100.0,
          "btts_home_matches": 1,
          "over_2_5_goals_home": 1,
          "over_0_5_ht_home": 1,
          "over_0_5_ft_home": 1,
          "clean_sheets_home": 0
        },
        "away": {
          "played": 2,
          "win": 0,
          "draw": 0,
          "lose": 2,
          "goals": {
            "for": 1,
            "against": 10
          },
          "form_visitor": "LL",
          "btts_away_matches": 1,
          "avg_corners_away_per_game": 3.0,
          "aproveitamento_away": 0.0,
          "over_2_5_goals_away": 1,
          "over_0_5_ht_away": 1,
          "over_0_5_ft_away": 0,
          "clean_sheets_away": 0
        },
        "update": "2025-09-23T00:00:00+00:00"
      },
      {
        "rank": 9,
        "team": {
          "id": 8740,
          "name": "Papua New Guinea National Team",
          "logo": "https://cdn.footystats.org/img/teams/papua-new-guinea-papua-new-guinea-national-team.png"
        },
        "points": 1,
        "goalsDiff": -3,
        "group": "International WC Qualification Oceania 2026",
        "status": "same",
        "description": "",
        "all": {
          "played": 3,
          "win": 0,
          "draw": 1,
          "lose": 2,
          "goals": {
            "for": 5,
            "against": 8
          },
          "form": "LDL",
          "btts_matches": 3,
          "avg_corners_per_game": -1.0,
          "aproveitamento": 11.1,
          "over_2_5_goals": 3,
          "over_0_5_ht": 1,
          "over_0_5_ft": 3,
          "clean_sheets": 0
        },
        "home": {
          "played": 2,
          "win": 0,
          "draw": 1,
          "lose": 1,
          "goals": {
            "for": 4,
            "against": 5
          },
          "form_home": "DL",
          "avg_corners_home_per_game": -1.0,
          "aproveitamento_home": 16.7,
          "btts_home_matches": 2,
          "over_2_5_goals_home": 2,
          "over_0_5_ht_home": 1,
          "over_0_5_ft_home": 2,
          "clean_sheets_home": 0
        },
        "away": {
          "played": 1,
          "win": 0,
          "draw": 0,
          "lose": 1,
          "goals": {
            "for": 1,
            "against": 3
          },
          "form_visitor": "L",
          "btts_away_matches": 1,
          "avg_corners_away_per_game": -1.0,
          "aproveitamento_away": 0.0,
          "over_2_5_goals_away": 1,
          "over_0_5_ht_away": 0,
          "over_0_5_ft_away": 1,
          "clean_sheets_away": 0
        },
        "update": "2025-09-23T00:00:00+00:00"
      },
      {
        "rank": 10,
        "team": {
          "id": 982799,
          "name": "Cook Islands National Team",
          "logo": "https://cdn.footystats.org/img/teams/cook-islands-cook-islands-national-team.png"
        },
        "points": 0,
        "goalsDiff": -2,
        "group": "International WC Qualification Oceania 2026",
        "status": "same",
        "description": "",
        "all": {
          "played": 1,
          "win": 0,
          "draw": 0,
          "lose": 1,
          "goals": {
            "for": 1,
            "against": 3
          },
          "form": "L",
          "btts_matches": 1,
          "avg_corners_per_game": -1.0,
          "aproveitamento": 0.0,
          "over_2_5_goals": 1,
          "over_0_5_ht": 0,
          "over_0_5_ft": 1,
          "clean_sheets": 0
        },
        "home": {
          "played": 1,
          "win": 0,
          "draw": 0,
          "lose": 1,
          "goals": {
            "for": 1,
            "against": 3
          },
          "form_home": "L",
          "avg_corners_home_per_game": -1.0,
          "aproveitamento_home": 0.0,
          "btts_home_matches": 1,
          "over_2_5_goals_home": 1,
          "over_0_5_ht_home": 0,
          "over_0_5_ft_home": 1,
          "clean_sheets_home": 0
        },
        "away": {
          "played": 0,
          "win": 0,
          "draw": 0,
          "lose": 0,
          "goals": {
            "for": 0,
            "against": 0
          },
          "form_visitor": "",
          "btts_away_matches": 0,
          "avg_corners_away_per_game": 0,
          "aproveitamento_away": 0,
          "over_2_5_goals_away": 0,
          "over_0_5_ht_away": 0,
          "over_0_5_ft_away": 0,
          "clean_sheets_away": 0
        },
        "update": "2025-09-23T00:00:00+00:00"
      },
      {
        "rank": 11,
        "team": {
          "id": 9024,
          "name": "American Samoa",
          "logo": "https://cdn.footystats.org/img/teams/american-samoa-american-samoa.png"
        },
        "points": 0,
        "goalsDiff": -2,
        "group": "International WC Qualification Oceania 2026",
        "status": "same",
        "description": "",
        "all": {
          "played": 1,
          "win": 0,
          "draw": 0,
          "lose": 1,
          "goals": {
            "for": 0,
            "against": 2
          },
          "form": "L",
          "btts_matches": 0,
          "avg_corners_per_game": -1.0,
          "aproveitamento": 0.0,
          "over_2_5_goals": 0,
          "over_0_5_ht": 0,
          "over_0_5_ft": 0,
          "clean_sheets": 0
        },
        "home": {
          "played": 1,
          "win": 0,
          "draw": 0,
          "lose": 1,
          "goals": {
            "for": 0,
            "against": 2
          },
          "form_home": "L",
          "avg_corners_home_per_game": -1.0,
          "aproveitamento_home": 0.0,
          "btts_home_matches": 0,
          "over_2_5_goals_home": 0,
          "over_0_5_ht_home": 0,
          "over_0_5_ft_home": 0,
          "clean_sheets_home": 0
        },
        "away": {
          "played": 0,
          "win": 0,
          "draw": 0,
          "lose": 0,
          "goals": {
            "for": 0,
            "against": 0
          },
          "form_visitor": "",
          "btts_away_matches": 0,
          "avg_corners_away_per_game": 0,
          "aproveitamento_away": 0,
          "over_2_5_goals_away": 0,
          "over_0_5_ht_away": 0,
          "over_0_5_ft_away": 0,
          "clean_sheets_away": 0
        },
        "update": "2025-09-23T00:00:00+00:00"
      }
    ]
  },
  "artilharia": {
    "international_wc_qualification_oceania": [
      {
        "jogador-nome": "Jogador_42458",
        "jogador-posicao": "Midfielder",
        "jogador-gols": 13,
        "jogador-assists": 0,
        "jogador-partidas": 12,
        "jogador-escudo": "https://cdn.footystats.org/img/teams/cook-islands-cook-islands-national-team.png",
        "jogador-foto": "https://cdn.footystats.org/img/players/-jogador_42458.png"
      },
      {
        "jogador-nome": "Christopher Grant Wood",
        "jogador-posicao": "Forward",
        "jogador-gols": 9,
        "jogador-assists": 0,
        "jogador-partidas": 5,
        "jogador-escudo": "https://cdn.footystats.org/img/teams/new-zealand-new-zealand-national-team.png",
        "jogador-foto": "https://cdn.footystats.org/img/players/new-zealand-chris-wood.png"
      },
      {
        "jogador-nome": "Elijah Henry Just",
        "jogador-posicao": "Midfielder",
        "jogador-gols": 4,
        "jogador-assists": 0,
        "jogador-partidas": 5,
        "jogador-escudo": "https://cdn.footystats.org/img/teams/new-zealand-new-zealand-national-team.png",
        "jogador-foto": "https://cdn.footystats.org/img/players/new-zealand-elijah-henry-just.png"
      },
      {
        "jogador-nome": "George Gope-Fenepej",
        "jogador-posicao": "Forward",
        "jogador-gols": 3,
        "jogador-assists": 1,
        "jogador-partidas": 5,
        "jogador-escudo": "https://cdn.footystats.org/img/teams/new-caledonia-new-caledonia-national-team.png",
        "jogador-foto": "https://cdn.footystats.org/img/players/new-caledonia-george-gope-fenepej.png"
      },
      {
        "jogador-nome": "Tyler Bindon",
        "jogador-posicao": "Defender",
        "jogador-gols": 3,
        "jogador-assists": 0,
        "jogador-partidas": 4,
        "jogador-escudo": "https://cdn.footystats.org/img/teams/new-zealand-new-zealand-national-team.png",
        "jogador-foto": "https://cdn.footystats.org/img/players/usa-tyler-bindon.png"
      },
      {
        "jogador-nome": "Roy Krishna",
        "jogador-posicao": "Forward",
        "jogador-gols": 3,
        "jogador-assists": 0,
        "jogador-partidas": 3,
        "jogador-escudo": "https://cdn.footystats.org/img/teams/fiji-fiji-national-team.png",
        "jogador-foto": "https://cdn.footystats.org/img/players/fiji-roy-krishna.png"
      },
      {
        "jogador-nome": "Joseph Athale",
        "jogador-posicao": "Midfielder",
        "jogador-gols": 3,
        "jogador-assists": 0,
        "jogador-partidas": 5,
        "jogador-escudo": "https://cdn.footystats.org/img/teams/new-caledonia-new-caledonia-national-team.png",
        "jogador-foto": "https://cdn.footystats.org/img/players/new-caledonia-joseph-athale.png"
      },
      {
        "jogador-nome": "Sarpeet Singh",
        "jogador-posicao": "Midfielder",
        "jogador-gols": 2,
        "jogador-assists": 3,
        "jogador-partidas": 4,
        "jogador-escudo": "https://cdn.footystats.org/img/teams/new-zealand-new-zealand-national-team.png",
        "jogador-foto": "https://cdn.footystats.org/img/players/new-zealand-sarpeet-singh.png"
      },
      {
        "jogador-nome": "Konstantinos Barbarouses",
        "jogador-posicao": "Forward",
        "jogador-gols": 2,
        "jogador-assists": 1,
        "jogador-partidas": 4,
        "jogador-escudo": "https://cdn.footystats.org/img/teams/new-zealand-new-zealand-national-team.png",
        "jogador-foto": "https://cdn.footystats.org/img/players/new-zealand-kosta-barbarouses.png"
      },
      {
        "jogador-nome": "Benjamin Peter Waine",
        "jogador-posicao": "Forward",
        "jogador-gols": 2,
        "jogador-assists": 1,
        "jogador-partidas": 4,
        "jogador-escudo": "https://cdn.footystats.org/img/teams/new-zealand-new-zealand-national-team.png",
        "jogador-foto": "https://cdn.footystats.org/img/players/new-zealand-ben-waine.png"
      },
      {
        "jogador-nome": "John Alick",
        "jogador-posicao": "Midfielder",
        "jogador-gols": 2,
        "jogador-assists": 0,
        "jogador-partidas": 3,
        "jogador-escudo": "https://cdn.footystats.org/img/teams/vanuatu-vanuatu-national-team.png",
        "jogador-foto": "https://cdn.footystats.org/img/players/vanuatu-john-alick.png"
      },
      {
        "jogador-nome": "Callum McCowatt",
        "jogador-posicao": "Midfielder",
        "jogador-gols": 2,
        "jogador-assists": 0,
        "jogador-partidas": 4,
        "jogador-escudo": "https://cdn.footystats.org/img/teams/new-zealand-new-zealand-national-team.png",
        "jogador-foto": "https://cdn.footystats.org/img/players/new-zealand-callum-mccowatt.png"
      },
      {
        "jogador-nome": "Benoît Mathon",
        "jogador-posicao": "Midfielder",
        "jogador-gols": 2,
        "jogador-assists": 0,
        "jogador-partidas": 4,
        "jogador-escudo": "https://cdn.footystats.org/img/teams/tahiti-tahiti-national-team.png",
        "jogador-foto": "https://cdn.footystats.org/img/players/france-benoit-mathon.png"
      },
      {
        "jogador-nome": "Matthew Jimmy David Garbett",
        "jogador-posicao": "Midfielder",
        "jogador-gols": 1,
        "jogador-assists": 5,
        "jogador-partidas": 5,
        "jogador-escudo": "https://cdn.footystats.org/img/teams/new-zealand-new-zealand-national-team.png",
        "jogador-foto": "https://cdn.footystats.org/img/players/new-zealand-matthew-garbett.png"
      },
      {
        "jogador-nome": "Timothy John Payne",
        "jogador-posicao": "Defender",
        "jogador-gols": 1,
        "jogador-assists": 4,
        "jogador-partidas": 3,
        "jogador-escudo": "https://cdn.footystats.org/img/teams/new-zealand-new-zealand-national-team.png",
        "jogador-foto": "https://cdn.footystats.org/img/players/new-zealand-timothy-john-payne.png"
      },
      {
        "jogador-nome": "Hemaloto Polovili",
        "jogador-posicao": "Midfielder",
        "jogador-gols": 1,
        "jogador-assists": 2,
        "jogador-partidas": 2,
        "jogador-escudo": "https://cdn.footystats.org/img/teams/tonga-tonga-national-team.png",
        "jogador-foto": "https://cdn.footystats.org/img/players/-hemaloto-polovili.png"
      },
      {
        "jogador-nome": "Francis De Vries",
        "jogador-posicao": "Midfielder",
        "jogador-gols": 1,
        "jogador-assists": 2,
        "jogador-partidas": 3,
        "jogador-escudo": "https://cdn.footystats.org/img/teams/new-zealand-new-zealand-national-team.png",
        "jogador-foto": "https://cdn.footystats.org/img/players/new-zealand-francis-de-vries.png"
      },
      {
        "jogador-nome": "Ulafala Sonasi",
        "jogador-posicao": "Midfielder",
        "jogador-gols": 1,
        "jogador-assists": 1,
        "jogador-partidas": 2,
        "jogador-escudo": "https://cdn.footystats.org/img/teams/tonga-tonga-national-team.png",
        "jogador-foto": "https://cdn.footystats.org/img/players/-ulafala-sonasi.png"
      },
      {
        "jogador-nome": "Raymond Gunemba",
        "jogador-posicao": "Forward",
        "jogador-gols": 1,
        "jogador-assists": 1,
        "jogador-partidas": 2,
        "jogador-escudo": "https://cdn.footystats.org/img/teams/papua-new-guinea-papua-new-guinea-national-team.png",
        "jogador-foto": "https://cdn.footystats.org/img/players/papua-new-guinea-raymond-gunemba.png"
      },
      {
        "jogador-nome": "Marko Stamenic",
        "jogador-posicao": "Midfielder",
        "jogador-gols": 1,
        "jogador-assists": 1,
        "jogador-partidas": 5,
        "jogador-escudo": "https://cdn.footystats.org/img/teams/new-zealand-new-zealand-national-team.png",
        "jogador-foto": "https://cdn.footystats.org/img/players/new-zealand-marko-stamenic.png"
      }
    ]
  }
}